pyembed-1.3.1-py2.7-nspkg.pth
pyembed/core/__init__.py
pyembed/core/consumer.py
pyembed/core/discovery.py
pyembed/core/error.py
pyembed/core/parse.py
pyembed/core/render.py
pyembed/core/response.py
pyembed/core/config/providers.json
pyembed-1.3.1.dist-info/DESCRIPTION.rst
pyembed-1.3.1.dist-info/METADATA
pyembed-1.3.1.dist-info/RECORD
pyembed-1.3.1.dist-info/WHEEL
pyembed-1.3.1.dist-info/metadata.json
pyembed-1.3.1.dist-info/namespace_packages.txt
pyembed-1.3.1.dist-info/top_level.txt
