Metadata-Version: 2.0
Name: pyembed
Version: 1.3.1
Summary: Python OEmbed consumer library with automatic discovery of producers
Home-page: http://pyembed.github.io
Author: Matt Thomson
Author-email: mattjohnthomson@gmail.com
License: Copyright (c) 2013 Matt Thomson
Requires-Dist: beautifulsoup4
Requires-Dist: requests
